phantomwright_driver/__init__.py
phantomwright_driver/__main__.py
phantomwright_driver/_repo_version.py
phantomwright_driver/py.typed
phantomwright_driver/_impl/__init__.py
phantomwright_driver/_impl/_api_structures.py
phantomwright_driver/_impl/_artifact.py
phantomwright_driver/_impl/_assertions.py
phantomwright_driver/_impl/_async_base.py
phantomwright_driver/_impl/_browser.py
phantomwright_driver/_impl/_browser_context.py
phantomwright_driver/_impl/_browser_type.py
phantomwright_driver/_impl/_cdp_session.py
phantomwright_driver/_impl/_clock.py
phantomwright_driver/_impl/_connection.py
phantomwright_driver/_impl/_console_message.py
phantomwright_driver/_impl/_dialog.py
phantomwright_driver/_impl/_download.py
phantomwright_driver/_impl/_driver.py
phantomwright_driver/_impl/_element_handle.py
phantomwright_driver/_impl/_errors.py
phantomwright_driver/_impl/_event_context_manager.py
phantomwright_driver/_impl/_fetch.py
phantomwright_driver/_impl/_file_chooser.py
phantomwright_driver/_impl/_frame.py
phantomwright_driver/_impl/_glob.py
phantomwright_driver/_impl/_greenlets.py
phantomwright_driver/_impl/_har_router.py
phantomwright_driver/_impl/_helper.py
phantomwright_driver/_impl/_impl_to_api_mapping.py
phantomwright_driver/_impl/_input.py
phantomwright_driver/_impl/_js_handle.py
phantomwright_driver/_impl/_json_pipe.py
phantomwright_driver/_impl/_local_utils.py
phantomwright_driver/_impl/_locator.py
phantomwright_driver/_impl/_map.py
phantomwright_driver/_impl/_network.py
phantomwright_driver/_impl/_object_factory.py
phantomwright_driver/_impl/_page.py
phantomwright_driver/_impl/_path_utils.py
phantomwright_driver/_impl/_playwright.py
phantomwright_driver/_impl/_selectors.py
phantomwright_driver/_impl/_set_input_files_helpers.py
phantomwright_driver/_impl/_str_utils.py
phantomwright_driver/_impl/_stream.py
phantomwright_driver/_impl/_sync_base.py
phantomwright_driver/_impl/_tracing.py
phantomwright_driver-1.58.0.dist-info/METADATA
phantomwright_driver-1.58.0.dist-info/WHEEL
phantomwright_driver-1.58.0.dist-info/entry_points.txt
phantomwright_driver-1.58.0.dist-info/top_level.txt
phantomwright_driver-1.58.0.dist-info/RECORD
phantomwright_driver-1.58.0.dist-info/licenses/LICENSE
