Metadata-Version: 2.4
Name: phantomwright-driver
Version: 1.58.0
Summary: Undetected Python version of the Playwright testing and automation library.
Author: Microsoft Corporation, patched by github.com/Kaliiiiiiiiii-Vinyzu/
License-Expression: Apache-2.0
Project-URL: homepage, https://github.com/StudentWan/phantomwright-driver-python
Project-URL: Release notes, https://github.com/StudentWan/phantomwright-driver-python/releases
Project-URL: Bug Reports, https://github.com/StudentWan/phantomwright-driver-python/issues
Project-URL: homeSource Codepage, https://github.com/StudentWan/phantomwright-driver-python
Classifier: Topic :: Software Development :: Testing
Classifier: Topic :: Internet :: WWW/HTTP :: Browsers
Classifier: Intended Audience :: Developers
Classifier: Programming Language :: Python :: 3
Classifier: Programming Language :: Python :: 3.9
Classifier: Programming Language :: Python :: 3.10
Classifier: Programming Language :: Python :: 3.11
Classifier: Programming Language :: Python :: 3.12
Classifier: Programming Language :: Python :: 3.13
Classifier: Operating System :: OS Independent
Requires-Python: >=3.9
License-File: LICENSE
Requires-Dist: pyee<14,>=13
Requires-Dist: greenlet<4.0.0,>=3.1.1
Dynamic: license-file
